rogii_solo/__init__.py
rogii_solo/base.py
rogii_solo/client.py
rogii_solo/comment.py
rogii_solo/earth_model.py
rogii_solo/exceptions.py
rogii_solo/horizon.py
rogii_solo/interpretation.py
rogii_solo/log.py
rogii_solo/mudlog.py
rogii_solo/project.py
rogii_solo/target_line.py
rogii_solo/topset.py
rogii_solo/trace.py
rogii_solo/trajectory.py
rogii_solo/types.py
rogii_solo/well.py
rogii_solo/calculations/__init__.py
rogii_solo/calculations/base.py
rogii_solo/calculations/constants.py
rogii_solo/calculations/converters.py
rogii_solo/calculations/enums.py
rogii_solo/calculations/exceptions.py
rogii_solo/calculations/interpretation.py
rogii_solo/calculations/trajectory.py
rogii_solo/calculations/types.py
rogii_solo/papi/__init__.py
rogii_solo/papi/base.py
rogii_solo/papi/client.py
rogii_solo/papi/exceptions.py
rogii_solo/papi/types.py
rogii_solo/utils/__init__.py
rogii_solo/utils/constants.py
rogii_solo/utils/objects.py
rogii_solo-0.5.4.dist-info/LICENSE.txt
rogii_solo-0.5.4.dist-info/METADATA
rogii_solo-0.5.4.dist-info/WHEEL
rogii_solo-0.5.4.dist-info/top_level.txt
rogii_solo-0.5.4.dist-info/RECORD
