Metadata-Version: 2.1
Name: rogii-solo
Version: 0.5.4
Summary: Rogii Solo is a Python SDK designed to make data scientists' work with Solo easier.
Author: Rogii Inc.
Author-email: support@rogii.com
License: Copyright 2022 Rogii Inc.
Project-URL: Homepage, https://www.rogii.com/
Project-URL: Documentation, https://kb.solo.cloud/Python+SDK
Project-URL: Issue Tracker, https://github.com/rogii-com/Python-SDK/issues
Project-URL: Source Code, https://github.com/rogii-com/Python-SDK
Project-URL: License Agreement, https://github.com/rogii-com/Python-SDK/blob/develop/LICENSE.txt
Keywords: rogii,solo,rogii solo,python sdk,data science,cloud data,data analysis,papi,starsteer,geology,drilling,geosteering
Classifier: Programming Language :: Python :: 3 :: Only
Classifier: Programming Language :: Python :: 3.10
Classifier: Programming Language :: Python :: 3.11
Classifier: Programming Language :: Python :: 3.12
Classifier: Programming Language :: Python :: 3.13
Classifier: License :: Other/Proprietary License
Classifier: Operating System :: OS Independent
Classifier: Development Status :: 4 - Beta
Classifier: Intended Audience :: Science/Research
Classifier: Environment :: Web Environment
Classifier: Topic :: Software Development :: Version Control :: Git
Classifier: Topic :: Software Development :: Testing :: Unit
Classifier: Topic :: Scientific/Engineering
Requires-Python: >=3.10
License-File: LICENSE.txt
Requires-Dist: requests==2.32.3
Requires-Dist: requests-oauthlib==2.0.0
Requires-Dist: pandas==2.2.3
Requires-Dist: numpy==2.1.1
Provides-Extra: dev
Requires-Dist: setuptools==75.1.0; extra == "dev"
Requires-Dist: wheel==0.44.0; extra == "dev"
Requires-Dist: build==0.8.0; extra == "dev"
Requires-Dist: twine==4.0.1; extra == "dev"
Requires-Dist: importlib-metadata==4.2.0; extra == "dev"
Requires-Dist: virtualenv==20.16.2; extra == "dev"
Requires-Dist: pre-commit==2.20.0; extra == "dev"
Requires-Dist: black==23.1.0; extra == "dev"
Requires-Dist: isort==5.12.0; extra == "dev"
Requires-Dist: flake8==5.0.4; extra == "dev"
Requires-Dist: pytest==7.1.2; extra == "dev"
